MANIFEST.in
README.rst
setup.py
artcamp/__init__.py
artcamp/cleaner.py
artcamp/lsi.py
artcamp/model.py
artcamp/utils.py
artcamp/vectorizers.py
artcamp.egg-info/PKG-INFO
artcamp.egg-info/SOURCES.txt
artcamp.egg-info/dependency_links.txt
artcamp.egg-info/not-zip-safe
artcamp.egg-info/requires.txt
artcamp.egg-info/top_level.txt
artcamp/data/name_list.pkl
artcamp/data/org_data.pkl
artcamp/data/test_index.pkl
artcamp/data/test_lsi.pkl
artcamp/data/tfidf.pkl
artcamp/data/tfidf_dict.pkl