Metadata-Version: 1.0
Name: artcamp
Version: 0.165
Summary: Query similarity between articles, orgs, and/or campaigns
Home-page: http://github.com/jwilber/artcamp
Author: Jared Wilber
Author-email: jwilber@classy.org
License: MIT
Platform: UNKNOWN
